JiqiZhixin2019GaofenJiaochengGithubNianduJingxuan/README.md
JiqiZhixin2019GaofenJiaochengGithubNianduJingxuan/__init__.py
JiqiZhixin2019GaofenJiaochengGithubNianduJingxuan/__main__.py
JiqiZhixin2019GaofenJiaochengGithubNianduJingxuan/file.epub
JiqiZhixin2019GaofenJiaochengGithubNianduJingxuan/index.html
JiqiZhixin2019GaofenJiaochengGithubNianduJingxuan/css/__init__.py
JiqiZhixin2019GaofenJiaochengGithubNianduJingxuan/css/annotations.css
JiqiZhixin2019GaofenJiaochengGithubNianduJingxuan/css/main.css
JiqiZhixin2019GaofenJiaochengGithubNianduJingxuan/css/normalize.css
JiqiZhixin2019GaofenJiaochengGithubNianduJingxuan/css/popup.css
JiqiZhixin2019GaofenJiaochengGithubNianduJingxuan/font/__init__.py
JiqiZhixin2019GaofenJiaochengGithubNianduJingxuan/font/fontello.eot
JiqiZhixin2019GaofenJiaochengGithubNianduJingxuan/font/fontello.svg
JiqiZhixin2019GaofenJiaochengGithubNianduJingxuan/font/fontello.ttf
JiqiZhixin2019GaofenJiaochengGithubNianduJingxuan/font/fontello.woff
JiqiZhixin2019GaofenJiaochengGithubNianduJingxuan/img/__init__.py
JiqiZhixin2019GaofenJiaochengGithubNianduJingxuan/img/annotator-glyph-sprite.png
JiqiZhixin2019GaofenJiaochengGithubNianduJingxuan/img/annotator-icon-sprite.png
JiqiZhixin2019GaofenJiaochengGithubNianduJingxuan/img/apple-touch-icon.png
JiqiZhixin2019GaofenJiaochengGithubNianduJingxuan/img/cancelfullscreen.png
JiqiZhixin2019GaofenJiaochengGithubNianduJingxuan/img/close.png
JiqiZhixin2019GaofenJiaochengGithubNianduJingxuan/img/fullscreen.png
JiqiZhixin2019GaofenJiaochengGithubNianduJingxuan/img/loader.gif
JiqiZhixin2019GaofenJiaochengGithubNianduJingxuan/img/menu-icon.png
JiqiZhixin2019GaofenJiaochengGithubNianduJingxuan/img/save.png
JiqiZhixin2019GaofenJiaochengGithubNianduJingxuan/img/saved.png
JiqiZhixin2019GaofenJiaochengGithubNianduJingxuan/img/settings-s.png
JiqiZhixin2019GaofenJiaochengGithubNianduJingxuan/img/settings.png
JiqiZhixin2019GaofenJiaochengGithubNianduJingxuan/img/star.png
jiqi_zhixin_2019_gaofen_jiaocheng_github_niandu_jingxuan-2024.3.5.0.dist-info/METADATA
jiqi_zhixin_2019_gaofen_jiaocheng_github_niandu_jingxuan-2024.3.5.0.dist-info/WHEEL
jiqi_zhixin_2019_gaofen_jiaocheng_github_niandu_jingxuan-2024.3.5.0.dist-info/entry_points.txt
jiqi_zhixin_2019_gaofen_jiaocheng_github_niandu_jingxuan-2024.3.5.0.dist-info/top_level.txt
jiqi_zhixin_2019_gaofen_jiaocheng_github_niandu_jingxuan-2024.3.5.0.dist-info/RECORD
